cloe_metadata_to_ddl/__init__.py
cloe_metadata_to_ddl/main.py
cloe_metadata_to_ddl/py.typed
cloe_metadata_to_ddl/utils/__init__.py
cloe_metadata_to_ddl/utils/create_ddl_from_db_model.py
cloe_metadata_to_ddl/utils/create_ddl_from_exec_sql.py
cloe_metadata_to_ddl/utils/create_stored_procedure_script.py
cloe_metadata_to_ddl/utils/templates/__init__.py
cloe_metadata_to_ddl/utils/templates/fabric_sparksql/__init__.py
cloe_metadata_to_ddl/utils/templates/fabric_sparksql/create_database.sql.j2
cloe_metadata_to_ddl/utils/templates/fabric_sparksql/create_schema.sql.j2
cloe_metadata_to_ddl/utils/templates/fabric_sparksql/create_table.sql.j2
cloe_metadata_to_ddl/utils/templates/snowflake_sql/__init__.py
cloe_metadata_to_ddl/utils/templates/snowflake_sql/create_database.sql.j2
cloe_metadata_to_ddl/utils/templates/snowflake_sql/create_schema.sql.j2
cloe_metadata_to_ddl/utils/templates/snowflake_sql/create_table.sql.j2
cloe_metadata_to_ddl/utils/templates/snowflake_sql/procedure_call.sql.j2
cloe_metadata_to_ddl/utils/templates/snowflake_sql/procedure_create.sql.j2
cloe_metadata_to_ddl/utils/templates/t_sql/__init__.py
cloe_metadata_to_ddl/utils/templates/t_sql/create_database.sql.j2
cloe_metadata_to_ddl/utils/templates/t_sql/create_schema.sql.j2
cloe_metadata_to_ddl/utils/templates/t_sql/create_table.sql.j2
cloe_metadata_to_ddl/utils/templates/t_sql/procedure_call.sql.j2
cloe_metadata_to_ddl/utils/templates/t_sql/procedure_create.sql.j2
cloe_metadata_to_ddl/utils/templating_engine/__init__.py
cloe_metadata_to_ddl/utils/templating_engine/jinja_env.py
cloe_metadata_to_ddl-1.1.6.dist-info/METADATA
cloe_metadata_to_ddl-1.1.6.dist-info/WHEEL
cloe_metadata_to_ddl-1.1.6.dist-info/entry_points.txt
cloe_metadata_to_ddl-1.1.6.dist-info/RECORD
